{"Country": "GRE", "Laps": [{"place": "12", "splitDistance": 125, "time": "00:00:11.318000"}, {"place": "14", "splitDistance": 250, "time": "00:00:18.630000"}, {"place": "13", "splitDistance": 375, "time": "00:00:25.354000"}, {"place": "13", "splitDistance": 500, "time": "00:00:32.148000"}, {"place": "13", "splitDistance": 625, "time": "00:00:39.225000"}, {"place": "13", "splitDistance": 750, "time": "00:00:46.578000"}], "Team": "Greece"}{"Country": "TRI", "Laps": [{"place": "14", "splitDistance": 125, "time": "00:00:11.429000"}, {"place": "13", "splitDistance": 250, "time": "00:00:18.618000"}, {"place": "14", "splitDistance": 375, "time": "00:00:25.417000"}, {"place": "14", "splitDistance": 500, "time": "00:00:32.429000"}, {"place": "15", "splitDistance": 625, "time": "00:00:39.517000"}, {"place": "15", "splitDistance": 750, "time": "00:00:46.729000"}], "Team": "Trinidad &Tobago"}{"Country": "COL", "Laps": [{"place": "15", "splitDistance": 125, "time": "00:00:11.717000"}, {"place": "15", "splitDistance": 250, "time": "00:00:19.086000"}, {"place": "15", "splitDistance": 375, "time": "00:00:25.789000"}, {"place": "15", "splitDistance": 500, "time": "00:00:32.625000"}, {"place": "14", "splitDistance": 625, "time": "00:00:39.490000"}, {"place": "14", "splitDistance": 750, "time": "00:00:46.594000"}], "Team": "Colombia"}{"Country": "CZE", "Laps": [{"place": "9", "splitDistance": 125, "time": "00:00:11.124000"}, {"place": "7", "splitDistance": 250, "time": "00:00:17.992000"}, {"place": "7", "splitDistance": 375, "time": "00:00:24.628000"}, {"place": "9", "splitDistance": 500, "time": "00:00:31.386000"}, {"place": "9", "splitDistance": 625, "time": "00:00:38.183000"}, {"place": "6", "splitDistance": 750, "time": "00:00:44.996000"}], "Team": "Czech Republic"}{"Country": "MAS", "Laps": [{"place": "8", "splitDistance": 125, "time": "00:00:11.103000"}, {"place": "8", "splitDistance": 250, "time": "00:00:18.016000"}, {"place": "9", "splitDistance": 375, "time": "00:00:24.747000"}, {"place": "10", "splitDistance": 500, "time": "00:00:31.621000"}, {"place": "11", "splitDistance": 625, "time": "00:00:38.594000"}, {"place": "12", "splitDistance": 750, "time": "00:00:45.771000"}], "Team": "Malaysia"}{"Country": "ESP", "Laps": [{"place": "10", "splitDistance": 125, "time": "00:00:11.276000"}, {"place": "10", "splitDistance": 250, "time": "00:00:18.250000"}, {"place": "10", "splitDistance": 375, "time": "00:00:24.886000"}, {"place": "11", "splitDistance": 500, "time": "00:00:31.697000"}, {"place": "10", "splitDistance": 625, "time": "00:00:38.567000"}, {"place": "10", "splitDistance": 750, "time": "00:00:45.513000"}], "Team": "Spain"}{"Country": "RUS", "Laps": [{"place": "13", "splitDistance": 125, "time": "00:00:11.408000"}, {"place": "12", "splitDistance": 250, "time": "00:00:18.433000"}, {"place": "11", "splitDistance": 375, "time": "00:00:24.942000"}, {"place": "8", "splitDistance": 500, "time": "00:00:31.322000"}, {"place": "8", "splitDistance": 625, "time": "00:00:38.096000"}, {"place": "9", "splitDistance": 750, "time": "00:00:45.201000"}], "Team": "Russia"}{"Country": "CHN", "Laps": [{"place": "11", "splitDistance": 125, "time": "00:00:11.317000"}, {"place": "11", "splitDistance": 250, "time": "00:00:18.413000"}, {"place": "12", "splitDistance": 375, "time": "00:00:25.196000"}, {"place": "12", "splitDistance": 500, "time": "00:00:32.018000"}, {"place": "12", "splitDistance": 625, "time": "00:00:38.749000"}, {"place": "11", "splitDistance": 750, "time": "00:00:45.713000"}], "Team": "China"}{"Country": "UKR", "Laps": [{"place": "4", "splitDistance": 125, "time": "00:00:10.901000"}, {"place": "6", "splitDistance": 250, "time": "00:00:17.940000"}, {"place": "6", "splitDistance": 375, "time": "00:00:24.526000"}, {"place": "5", "splitDistance": 500, "time": "00:00:31.259000"}, {"place": "5", "splitDistance": 625, "time": "00:00:37.972000"}, {"place": "5", "splitDistance": 750, "time": "00:00:44.865000"}], "Team": "Ukraine"}{"Country": "POL", "Laps": [{"place": "3", "splitDistance": 125, "time": "00:00:10.780000"}, {"place": "2", "splitDistance": 250, "time": "00:00:17.575000"}, {"place": "3", "splitDistance": 375, "time": "00:00:24.017000"}, {"place": "3", "splitDistance": 500, "time": "00:00:30.611000"}, {"place": "4", "splitDistance": 625, "time": "00:00:37.299000"}, {"place": "4", "splitDistance": 750, "time": "00:00:44.115000"}], "Team": "Poland"}{"Country": "AUS", "Laps": [{"place": "2", "splitDistance": 125, "time": "00:00:10.727000"}, {"place": "3", "splitDistance": 250, "time": "00:00:17.583000"}, {"place": "4", "splitDistance": 375, "time": "00:00:24.047000"}, {"place": "4", "splitDistance": 500, "time": "00:00:30.658000"}, {"place": "3", "splitDistance": 625, "time": "00:00:37.263000"}, {"place": "3", "splitDistance": 750, "time": "00:00:43.911000"}], "Team": "Australia"}{"Country": "GER", "Laps": [{"place": "5", "splitDistance": 125, "time": "00:00:10.903000"}, {"place": "4", "splitDistance": 250, "time": "00:00:17.653000"}, {"place": "2", "splitDistance": 375, "time": "00:00:23.999000"}, {"place": "2", "splitDistance": 500, "time": "00:00:30.394000"}, {"place": "2", "splitDistance": 625, "time": "00:00:36.947000"}, {"place": "2", "splitDistance": 750, "time": "00:00:43.738000"}], "Team": "Germany"}{"Country": "GBR", "Laps": [{"place": "7", "splitDistance": 125, "time": "00:00:11.082000"}, {"place": "9", "splitDistance": 250, "time": "00:00:18.179000"}, {"place": "8", "splitDistance": 375, "time": "00:00:24.737000"}, {"place": "7", "splitDistance": 500, "time": "00:00:31.318000"}, {"place": "6", "splitDistance": 625, "time": "00:00:38.050000"}, {"place": "7", "splitDistance": 750, "time": "00:00:44.999000"}], "Team": "Great Britain"}{"Country": "NED", "Laps": [{"place": "1", "splitDistance": 125, "time": "00:00:10.701000"}, {"place": "1", "splitDistance": 250, "time": "00:00:17.343000"}, {"place": "1", "splitDistance": 375, "time": "00:00:23.701000"}, {"place": "1", "splitDistance": 500, "time": "00:00:30.187000"}, {"place": "1", "splitDistance": 625, "time": "00:00:36.724000"}, {"place": "1", "splitDistance": 750, "time": "00:00:43.614000"}], "Team": "Netherlands"}{"Country": "FRA", "Laps": [{"place": "6", "splitDistance": 125, "time": "00:00:10.931000"}, {"place": "5", "splitDistance": 250, "time": "00:00:17.865000"}, {"place": "5", "splitDistance": 375, "time": "00:00:24.478000"}, {"place": "6", "splitDistance": 500, "time": "00:00:31.265000"}, {"place": "7", "splitDistance": 625, "time": "00:00:38.084000"}, {"place": "8", "splitDistance": 750, "time": "00:00:45.139000"}], "Team": "France"}