{"Country": "NED", "Laps": [{"place": "2", "splitDistance": 125, "time": "00:00:14.304000"}, {"place": "2", "splitDistance": 250, "time": "00:00:23.279000"}, {"place": "2", "splitDistance": 375, "time": "00:00:32.051000"}, {"place": "2", "splitDistance": 500, "time": "00:00:40.852000"}, {"place": "2", "splitDistance": 625, "time": "00:00:49.753000"}, {"place": "2", "splitDistance": 750, "time": "00:00:58.728000"}, {"place": "2", "splitDistance": 875, "time": "00:01:07.767000"}, {"place": "2", "splitDistance": 1000, "time": "00:01:16.868000"}, {"place": "2", "splitDistance": 1125, "time": "00:01:25.942000"}, {"place": "2", "splitDistance": 1250, "time": "00:01:35.059000"}, {"place": "2", "splitDistance": 1375, "time": "00:01:44.181000"}, {"place": "2", "splitDistance": 1500, "time": "00:01:53.347000"}, {"place": "2", "splitDistance": 1625, "time": "00:02:02.538000"}, {"place": "2", "splitDistance": 1750, "time": "00:02:11.763000"}, {"place": "2", "splitDistance": 1875, "time": "00:02:20.963000"}, {"place": "2", "splitDistance": 2000, "time": "00:02:30.101000"}, {"place": "2", "splitDistance": 2125, "time": "00:02:39.167000"}, {"place": "2", "splitDistance": 2250, "time": "00:02:48.184000"}, {"place": "2", "splitDistance": 2375, "time": "00:02:57.161000"}, {"place": "2", "splitDistance": 2500, "time": "00:03:06.131000"}, {"place": "2", "splitDistance": 2625, "time": "00:03:15.101000"}, {"place": "2", "splitDistance": 2750, "time": "00:03:24.025000"}, {"place": "1", "splitDistance": 2875, "time": "00:03:32.820000"}, {"place": "1", "splitDistance": 3000, "time": "00:03:41.522000"}], "firstName": "Vera", "lastName": "KOEDOODER"}{"Country": "ESP", "Laps": [{"place": "1", "splitDistance": 125, "time": "00:00:14.271000"}, {"place": "1", "splitDistance": 250, "time": "00:00:23.111000"}, {"place": "1", "splitDistance": 375, "time": "00:00:31.830000"}, {"place": "1", "splitDistance": 500, "time": "00:00:40.602000"}, {"place": "1", "splitDistance": 625, "time": "00:00:49.379000"}, {"place": "1", "splitDistance": 750, "time": "00:00:58.234000"}, {"place": "1", "splitDistance": 875, "time": "00:01:07.123000"}, {"place": "1", "splitDistance": 1000, "time": "00:01:16.057000"}, {"place": "1", "splitDistance": 1125, "time": "00:01:24.997000"}, {"place": "1", "splitDistance": 1250, "time": "00:01:33.919000"}, {"place": "1", "splitDistance": 1375, "time": "00:01:42.906000"}, {"place": "1", "splitDistance": 1500, "time": "00:01:51.906000"}, {"place": "1", "splitDistance": 1625, "time": "00:02:00.959000"}, {"place": "1", "splitDistance": 1750, "time": "00:02:10.065000"}, {"place": "1", "splitDistance": 1875, "time": "00:02:19.154000"}, {"place": "1", "splitDistance": 2000, "time": "00:02:28.267000"}, {"place": "1", "splitDistance": 2125, "time": "00:02:37.395000"}, {"place": "1", "splitDistance": 2250, "time": "00:02:46.621000"}, {"place": "1", "splitDistance": 2375, "time": "00:02:55.850000"}, {"place": "1", "splitDistance": 2500, "time": "00:03:05.098000"}, {"place": "1", "splitDistance": 2625, "time": "00:03:14.360000"}, {"place": "1", "splitDistance": 2750, "time": "00:03:23.666000"}, {"place": "2", "splitDistance": 2875, "time": "00:03:32.960000"}, {"place": "2", "splitDistance": 3000, "time": "00:03:42.255000"}], "firstName": "Leire", "lastName": "OLABERRIA DORRONSORO"}{"Country": "GBR", "Laps": [{"place": "2", "splitDistance": 125, "time": "00:00:14.174000"}, {"place": "1", "splitDistance": 250, "time": "00:00:22.833000"}, {"place": "1", "splitDistance": 375, "time": "00:00:31.118000"}, {"place": "1", "splitDistance": 500, "time": "00:00:39.369000"}, {"place": "1", "splitDistance": 625, "time": "00:00:47.710000"}, {"place": "1", "splitDistance": 750, "time": "00:00:56.162000"}, {"place": "1", "splitDistance": 875, "time": "00:01:04.720000"}, {"place": "1", "splitDistance": 1000, "time": "00:01:13.349000"}, {"place": "1", "splitDistance": 1125, "time": "00:01:22.009000"}, {"place": "1", "splitDistance": 1250, "time": "00:01:30.653000"}, {"place": "1", "splitDistance": 1375, "time": "00:01:39.301000"}, {"place": "1", "splitDistance": 1500, "time": "00:01:47.905000"}, {"place": "1", "splitDistance": 1625, "time": "00:01:56.524000"}, {"place": "1", "splitDistance": 1750, "time": "00:02:05.177000"}, {"place": "1", "splitDistance": 1875, "time": "00:02:13.853000"}, {"place": "1", "splitDistance": 2000, "time": "00:02:22.563000"}, {"place": "1", "splitDistance": 2125, "time": "00:02:31.242000"}, {"place": "1", "splitDistance": 2250, "time": "00:02:39.921000"}, {"place": "1", "splitDistance": 2375, "time": "00:02:48.617000"}, {"place": "1", "splitDistance": 2500, "time": "00:02:57.286000"}, {"place": "1", "splitDistance": 2625, "time": "00:03:05.988000"}, {"place": "1", "splitDistance": 2750, "time": "00:03:14.673000"}, {"place": "1", "splitDistance": 2875, "time": "00:03:23.267000"}, {"place": "1", "splitDistance": 3000, "time": "00:03:31.929000"}], "firstName": "Wendy", "lastName": "HOUVENAGHEL"}