[{"Country": "TPE ", "Laps": [{"place": -1, "splitDistance": 125, "time": "00:00:13.635000"}, {"place": 14, "splitDistance": 250, "time": "00:00:21.777000"}, {"place": -1, "splitDistance": 375, "time": "00:00:29.654000"}, {"place": 16, "splitDistance": 500, "time": "00:00:37.395000"}, {"place": -1, "splitDistance": 625, "time": "00:00:45.242000"}, {"place": 17, "splitDistance": 750, "time": "00:00:53.049000"}, {"place": -1, "splitDistance": 875, "time": "00:01:00.987000"}, {"place": 17, "splitDistance": 1000, "time": "00:01:08.874000"}, {"place": -1, "splitDistance": 1125, "time": "00:01:16.890000"}, {"place": 17, "splitDistance": 1250, "time": "00:01:24.732000"}, {"place": -1, "splitDistance": 1375, "time": "00:01:32.542000"}, {"place": 17, "splitDistance": 1500, "time": "00:01:40.495000"}, {"place": -1, "splitDistance": 1625, "time": "00:01:48.435000"}, {"place": 17, "splitDistance": 1750, "time": "00:01:56.525000"}, {"place": -1, "splitDistance": 1875, "time": "00:02:04.635000"}, {"place": 17, "splitDistance": 2000, "time": "00:02:12.858000"}, {"place": -1, "splitDistance": 2125, "time": "00:02:20.970000"}, {"place": 17, "splitDistance": 2250, "time": "00:02:29.234000"}, {"place": -1, "splitDistance": 2375, "time": "00:02:37.183000"}, {"place": 17, "splitDistance": 2500, "time": "00:02:45.078000"}, {"place": -1, "splitDistance": 2625, "time": "00:02:52.960000"}, {"place": 17, "splitDistance": 2750, "time": "00:03:01.020000"}, {"place": -1, "splitDistance": 2875, "time": "00:03:09.336000"}, {"place": 17, "splitDistance": 3000, "time": "00:03:17.883000"}, {"place": -1, "splitDistance": 3125, "time": "00:03:26.253000"}, {"place": 17, "splitDistance": 3250, "time": "00:03:34.850000"}, {"place": -1, "splitDistance": 3375, "time": "00:03:43.711000"}, {"place": 17, "splitDistance": 3500, "time": "00:03:52.736000"}, {"place": -1, "splitDistance": 3625, "time": "00:04:01.978000"}, {"place": 17, "splitDistance": 3750, "time": "00:04:11.313000"}, {"place": -1, "splitDistance": 3875, "time": "00:04:20.544000"}, {"place": 17, "splitDistance": 4000, "time": "00:04:29.539000"}], "Team": "Chinese Taipei"}, {"Country": "USA ", "Laps": [{"place": -1, "splitDistance": 125, "time": "00:00:13.485000"}, {"place": 8, "splitDistance": 250, "time": "00:00:21.359000"}, {"place": -1, "splitDistance": 375, "time": "00:00:29.011000"}, {"place": 11, "splitDistance": 500, "time": "00:00:36.573000"}, {"place": -1, "splitDistance": 625, "time": "00:00:44.328000"}, {"place": 14, "splitDistance": 750, "time": "00:00:52.221000"}, {"place": -1, "splitDistance": 875, "time": "00:01:00.257000"}, {"place": 15, "splitDistance": 1000, "time": "00:01:08.131000"}, {"place": -1, "splitDistance": 1125, "time": "00:01:15.906000"}, {"place": 14, "splitDistance": 1250, "time": "00:01:23.651000"}, {"place": -1, "splitDistance": 1375, "time": "00:01:31.479000"}, {"place": 14, "splitDistance": 1500, "time": "00:01:39.101000"}, {"place": -1, "splitDistance": 1625, "time": "00:01:46.627000"}, {"place": 14, "splitDistance": 1750, "time": "00:01:54.296000"}, {"place": -1, "splitDistance": 1875, "time": "00:02:02.128000"}, {"place": 14, "splitDistance": 2000, "time": "00:02:09.812000"}, {"place": -1, "splitDistance": 2125, "time": "00:02:17.625000"}, {"place": 14, "splitDistance": 2250, "time": "00:02:25.354000"}, {"place": -1, "splitDistance": 2375, "time": "00:02:33.073000"}, {"place": 14, "splitDistance": 2500, "time": "00:02:40.982000"}, {"place": -1, "splitDistance": 2625, "time": "00:02:48.740000"}, {"place": 14, "splitDistance": 2750, "time": "00:02:56.425000"}, {"place": -1, "splitDistance": 2875, "time": "00:03:04.186000"}, {"place": 14, "splitDistance": 3000, "time": "00:03:12.071000"}, {"place": -1, "splitDistance": 3125, "time": "00:03:19.831000"}, {"place": 14, "splitDistance": 3250, "time": "00:03:27.934000"}, {"place": -1, "splitDistance": 3375, "time": "00:03:35.958000"}, {"place": 13, "splitDistance": 3500, "time": "00:03:43.900000"}, {"place": -1, "splitDistance": 3625, "time": "00:03:51.816000"}, {"place": 13, "splitDistance": 3750, "time": "00:03:59.934000"}, {"place": -1, "splitDistance": 3875, "time": "00:04:07.668000"}, {"place": 13, "splitDistance": 4000, "time": "00:04:15.374000"}], "Team": "United States"}, {"Country": "CHN ", "Laps": [{"place": -1, "splitDistance": 125, "time": "00:00:13.142000"}, {"place": 4, "splitDistance": 250, "time": "00:00:20.907000"}, {"place": -1, "splitDistance": 375, "time": "00:00:28.449000"}, {"place": 3, "splitDistance": 500, "time": "00:00:35.753000"}, {"place": -1, "splitDistance": 625, "time": "00:00:43.073000"}, {"place": 4, "splitDistance": 750, "time": "00:00:50.382000"}, {"place": -1, "splitDistance": 875, "time": "00:00:57.818000"}, {"place": 4, "splitDistance": 1000, "time": "00:01:05.194000"}, {"place": -1, "splitDistance": 1125, "time": "00:01:12.814000"}, {"place": 4, "splitDistance": 1250, "time": "00:01:20.371000"}, {"place": -1, "splitDistance": 1375, "time": "00:01:28.063000"}, {"place": 4, "splitDistance": 1500, "time": "00:01:35.603000"}, {"place": -1, "splitDistance": 1625, "time": "00:01:43.301000"}, {"place": 4, "splitDistance": 1750, "time": "00:01:50.875000"}, {"place": -1, "splitDistance": 1875, "time": "00:01:58.440000"}, {"place": 6, "splitDistance": 2000, "time": "00:02:06.141000"}, {"place": -1, "splitDistance": 2125, "time": "00:02:13.734000"}, {"place": 6, "splitDistance": 2250, "time": "00:02:21.574000"}, {"place": -1, "splitDistance": 2375, "time": "00:02:29.345000"}, {"place": 8, "splitDistance": 2500, "time": "00:02:37.298000"}, {"place": -1, "splitDistance": 2625, "time": "00:02:45.323000"}, {"place": 9, "splitDistance": 2750, "time": "00:02:53.045000"}, {"place": -1, "splitDistance": 2875, "time": "00:03:00.710000"}, {"place": 9, "splitDistance": 3000, "time": "00:03:08.561000"}, {"place": -1, "splitDistance": 3125, "time": "00:03:16.315000"}, {"place": 9, "splitDistance": 3250, "time": "00:03:24.145000"}, {"place": -1, "splitDistance": 3375, "time": "00:03:32.168000"}, {"place": 10, "splitDistance": 3500, "time": "00:03:40.235000"}, {"place": -1, "splitDistance": 3625, "time": "00:03:48.389000"}, {"place": 12, "splitDistance": 3750, "time": "00:03:56.216000"}, {"place": -1, "splitDistance": 3875, "time": "00:04:03.956000"}, {"place": 12, "splitDistance": 4000, "time": "00:04:11.661000"}], "Team": "China"}, {"Country": "KAZ ", "Laps": [{"place": -1, "splitDistance": 125, "time": "00:00:13.894000"}, {"place": 16, "splitDistance": 250, "time": "00:00:21.958000"}, {"place": -1, "splitDistance": 375, "time": "00:00:29.739000"}, {"place": 15, "splitDistance": 500, "time": "00:00:37.322000"}, {"place": -1, "splitDistance": 625, "time": "00:00:44.991000"}, {"place": 15, "splitDistance": 750, "time": "00:00:52.543000"}, {"place": -1, "splitDistance": 875, "time": "00:01:00.235000"}, {"place": 14, "splitDistance": 1000, "time": "00:01:08.074000"}, {"place": -1, "splitDistance": 1125, "time": "00:01:16.093000"}, {"place": 15, "splitDistance": 1250, "time": "00:01:23.971000"}, {"place": -1, "splitDistance": 1375, "time": "00:01:32.007000"}, {"place": 15, "splitDistance": 1500, "time": "00:01:39.824000"}, {"place": -1, "splitDistance": 1625, "time": "00:01:47.661000"}, {"place": 15, "splitDistance": 1750, "time": "00:01:55.323000"}, {"place": -1, "splitDistance": 1875, "time": "00:02:03.151000"}, {"place": 15, "splitDistance": 2000, "time": "00:02:11.219000"}, {"place": -1, "splitDistance": 2125, "time": "00:02:19.117000"}, {"place": 15, "splitDistance": 2250, "time": "00:02:27.264000"}, {"place": -1, "splitDistance": 2375, "time": "00:02:35.109000"}, {"place": 15, "splitDistance": 2500, "time": "00:02:42.934000"}, {"place": -1, "splitDistance": 2625, "time": "00:02:50.894000"}, {"place": 15, "splitDistance": 2750, "time": "00:02:58.628000"}, {"place": -1, "splitDistance": 2875, "time": "00:03:06.558000"}, {"place": 15, "splitDistance": 3000, "time": "00:03:14.706000"}, {"place": -1, "splitDistance": 3125, "time": "00:03:23.085000"}, {"place": 15, "splitDistance": 3250, "time": "00:03:31.235000"}, {"place": -1, "splitDistance": 3375, "time": "00:03:39.599000"}, {"place": 16, "splitDistance": 3500, "time": "00:03:47.571000"}, {"place": -1, "splitDistance": 3625, "time": "00:03:55.581000"}, {"place": 16, "splitDistance": 3750, "time": "00:04:03.949000"}, {"place": -1, "splitDistance": 3875, "time": "00:04:12.421000"}, {"place": 16, "splitDistance": 4000, "time": "00:04:21.010000"}], "Team": "Kazakhstan"}, {"Country": "ITA ", "Laps": [{"place": -1, "splitDistance": 125, "time": "00:00:14.031000"}, {"place": 17, "splitDistance": 250, "time": "00:00:22.222000"}, {"place": -1, "splitDistance": 375, "time": "00:00:30.120000"}, {"place": 17, "splitDistance": 500, "time": "00:00:37.725000"}, {"place": -1, "splitDistance": 625, "time": "00:00:45.359000"}, {"place": 16, "splitDistance": 750, "time": "00:00:53.020000"}, {"place": -1, "splitDistance": 875, "time": "00:01:00.806000"}, {"place": 16, "splitDistance": 1000, "time": "00:01:08.521000"}, {"place": -1, "splitDistance": 1125, "time": "00:01:16.437000"}, {"place": 16, "splitDistance": 1250, "time": "00:01:24.203000"}, {"place": -1, "splitDistance": 1375, "time": "00:01:32.076000"}, {"place": 16, "splitDistance": 1500, "time": "00:01:39.846000"}, {"place": -1, "splitDistance": 1625, "time": "00:01:47.752000"}, {"place": 16, "splitDistance": 1750, "time": "00:01:55.619000"}, {"place": -1, "splitDistance": 1875, "time": "00:02:03.616000"}, {"place": 16, "splitDistance": 2000, "time": "00:02:11.507000"}, {"place": -1, "splitDistance": 2125, "time": "00:02:19.576000"}, {"place": 16, "splitDistance": 2250, "time": "00:02:27.371000"}, {"place": -1, "splitDistance": 2375, "time": "00:02:35.252000"}, {"place": 16, "splitDistance": 2500, "time": "00:02:43.183000"}, {"place": -1, "splitDistance": 2625, "time": "00:02:51.268000"}, {"place": 16, "splitDistance": 2750, "time": "00:02:59.205000"}, {"place": -1, "splitDistance": 2875, "time": "00:03:07.296000"}, {"place": 16, "splitDistance": 3000, "time": "00:03:15.229000"}, {"place": -1, "splitDistance": 3125, "time": "00:03:23.484000"}, {"place": 16, "splitDistance": 3250, "time": "00:03:31.294000"}, {"place": -1, "splitDistance": 3375, "time": "00:03:39.167000"}, {"place": 15, "splitDistance": 3500, "time": "00:03:47.173000"}, {"place": -1, "splitDistance": 3625, "time": "00:03:55.298000"}, {"place": 15, "splitDistance": 3750, "time": "00:04:03.786000"}, {"place": -1, "splitDistance": 3875, "time": "00:04:12.123000"}, {"place": 15, "splitDistance": 4000, "time": "00:04:20.123000"}], "Team": "Italy"}, {"Country": "KOR ", "Laps": [{"place": -1, "splitDistance": 125, "time": "00:00:13.481000"}, {"place": 11, "splitDistance": 250, "time": "00:00:21.478000"}, {"place": -1, "splitDistance": 375, "time": "00:00:28.993000"}, {"place": 9, "splitDistance": 500, "time": "00:00:36.520000"}, {"place": -1, "splitDistance": 625, "time": "00:00:43.888000"}, {"place": 9, "splitDistance": 750, "time": "00:00:51.391000"}, {"place": -1, "splitDistance": 875, "time": "00:00:58.800000"}, {"place": 9, "splitDistance": 1000, "time": "00:01:06.393000"}, {"place": -1, "splitDistance": 1125, "time": "00:01:13.873000"}, {"place": 9, "splitDistance": 1250, "time": "00:01:21.463000"}, {"place": -1, "splitDistance": 1375, "time": "00:01:28.941000"}, {"place": 9, "splitDistance": 1500, "time": "00:01:36.567000"}, {"place": -1, "splitDistance": 1625, "time": "00:01:44.030000"}, {"place": 7, "splitDistance": 1750, "time": "00:01:51.629000"}, {"place": -1, "splitDistance": 1875, "time": "00:01:59.057000"}, {"place": 7, "splitDistance": 2000, "time": "00:02:06.618000"}, {"place": -1, "splitDistance": 2125, "time": "00:02:14.057000"}, {"place": 7, "splitDistance": 2250, "time": "00:02:21.650000"}, {"place": -1, "splitDistance": 2375, "time": "00:02:29.171000"}, {"place": 7, "splitDistance": 2500, "time": "00:02:36.865000"}, {"place": -1, "splitDistance": 2625, "time": "00:02:44.371000"}, {"place": 6, "splitDistance": 2750, "time": "00:02:52.063000"}, {"place": -1, "splitDistance": 2875, "time": "00:02:59.517000"}, {"place": 6, "splitDistance": 3000, "time": "00:03:07.161000"}, {"place": -1, "splitDistance": 3125, "time": "00:03:14.694000"}, {"place": 5, "splitDistance": 3250, "time": "00:03:22.418000"}, {"place": -1, "splitDistance": 3375, "time": "00:03:30.214000"}, {"place": 5, "splitDistance": 3500, "time": "00:03:37.910000"}, {"place": -1, "splitDistance": 3625, "time": "00:03:45.776000"}, {"place": 5, "splitDistance": 3750, "time": "00:03:53.496000"}, {"place": -1, "splitDistance": 3875, "time": "00:04:01.252000"}, {"place": 5, "splitDistance": 4000, "time": "00:04:09.091000"}], "Team": "Korea"}, {"Country": "HKG ", "Laps": [{"place": -1, "splitDistance": 125, "time": "00:00:13.587000"}, {"place": 9, "splitDistance": 250, "time": "00:00:21.360000"}, {"place": -1, "splitDistance": 375, "time": "00:00:28.960000"}, {"place": 10, "splitDistance": 500, "time": "00:00:36.557000"}, {"place": -1, "splitDistance": 625, "time": "00:00:44.281000"}, {"place": 10, "splitDistance": 750, "time": "00:00:51.838000"}, {"place": -1, "splitDistance": 875, "time": "00:00:59.496000"}, {"place": 10, "splitDistance": 1000, "time": "00:01:06.977000"}, {"place": -1, "splitDistance": 1125, "time": "00:01:14.527000"}, {"place": 11, "splitDistance": 1250, "time": "00:01:22.212000"}, {"place": -1, "splitDistance": 1375, "time": "00:01:29.936000"}, {"place": 11, "splitDistance": 1500, "time": "00:01:37.484000"}, {"place": -1, "splitDistance": 1625, "time": "00:01:45.143000"}, {"place": 10, "splitDistance": 1750, "time": "00:01:52.710000"}, {"place": -1, "splitDistance": 1875, "time": "00:02:00.364000"}, {"place": 11, "splitDistance": 2000, "time": "00:02:08.122000"}, {"place": -1, "splitDistance": 2125, "time": "00:02:16.082000"}, {"place": 13, "splitDistance": 2250, "time": "00:02:24.026000"}, {"place": -1, "splitDistance": 2375, "time": "00:02:31.695000"}, {"place": 13, "splitDistance": 2500, "time": "00:02:39.499000"}, {"place": -1, "splitDistance": 2625, "time": "00:02:47.187000"}, {"place": 12, "splitDistance": 2750, "time": "00:02:54.924000"}, {"place": -1, "splitDistance": 2875, "time": "00:03:02.938000"}, {"place": 13, "splitDistance": 3000, "time": "00:03:11.168000"}, {"place": -1, "splitDistance": 3125, "time": "00:03:19.654000"}, {"place": 13, "splitDistance": 3250, "time": "00:03:27.713000"}, {"place": -1, "splitDistance": 3375, "time": "00:03:35.754000"}, {"place": 14, "splitDistance": 3500, "time": "00:03:44.017000"}, {"place": -1, "splitDistance": 3625, "time": "00:03:52.679000"}, {"place": 14, "splitDistance": 3750, "time": "00:04:01.476000"}, {"place": -1, "splitDistance": 3875, "time": "00:04:10.098000"}, {"place": 14, "splitDistance": 4000, "time": "00:04:18.867000"}], "Team": "Hong Kong"}, {"Country": "UKR ", "Laps": [{"place": -1, "splitDistance": 125, "time": "00:00:13.462000"}, {"place": 6, "splitDistance": 250, "time": "00:00:21.261000"}, {"place": -1, "splitDistance": 375, "time": "00:00:28.755000"}, {"place": 7, "splitDistance": 500, "time": "00:00:36.167000"}, {"place": -1, "splitDistance": 625, "time": "00:00:43.758000"}, {"place": 7, "splitDistance": 750, "time": "00:00:51.162000"}, {"place": -1, "splitDistance": 875, "time": "00:00:58.649000"}, {"place": 6, "splitDistance": 1000, "time": "00:01:05.959000"}, {"place": -1, "splitDistance": 1125, "time": "00:01:13.409000"}, {"place": 6, "splitDistance": 1250, "time": "00:01:20.791000"}, {"place": -1, "splitDistance": 1375, "time": "00:01:28.335000"}, {"place": 6, "splitDistance": 1500, "time": "00:01:35.829000"}, {"place": -1, "splitDistance": 1625, "time": "00:01:43.491000"}, {"place": 6, "splitDistance": 1750, "time": "00:01:51.009000"}, {"place": -1, "splitDistance": 1875, "time": "00:01:58.607000"}, {"place": 5, "splitDistance": 2000, "time": "00:02:06.054000"}, {"place": -1, "splitDistance": 2125, "time": "00:02:13.635000"}, {"place": 4, "splitDistance": 2250, "time": "00:02:21.128000"}, {"place": -1, "splitDistance": 2375, "time": "00:02:28.744000"}, {"place": 5, "splitDistance": 2500, "time": "00:02:36.433000"}, {"place": -1, "splitDistance": 2625, "time": "00:02:44.151000"}, {"place": 5, "splitDistance": 2750, "time": "00:02:51.697000"}, {"place": -1, "splitDistance": 2875, "time": "00:02:59.386000"}, {"place": 5, "splitDistance": 3000, "time": "00:03:07.057000"}, {"place": -1, "splitDistance": 3125, "time": "00:03:14.857000"}, {"place": 6, "splitDistance": 3250, "time": "00:03:22.544000"}, {"place": -1, "splitDistance": 3375, "time": "00:03:30.415000"}, {"place": 7, "splitDistance": 3500, "time": "00:03:38.227000"}, {"place": -1, "splitDistance": 3625, "time": "00:03:45.797000"}, {"place": 6, "splitDistance": 3750, "time": "00:03:53.573000"}, {"place": -1, "splitDistance": 3875, "time": "00:04:01.339000"}, {"place": 6, "splitDistance": 4000, "time": "00:04:09.374000"}], "Team": "Ukraine"}, {"Country": "SUI ", "Laps": [{"place": -1, "splitDistance": 125, "time": "00:00:13.655000"}, {"place": 15, "splitDistance": 250, "time": "00:00:21.937000"}, {"place": -1, "splitDistance": 375, "time": "00:00:29.456000"}, {"place": 14, "splitDistance": 500, "time": "00:00:36.934000"}, {"place": -1, "splitDistance": 625, "time": "00:00:44.347000"}, {"place": 11, "splitDistance": 750, "time": "00:00:51.992000"}, {"place": -1, "splitDistance": 875, "time": "00:00:59.486000"}, {"place": 11, "splitDistance": 1000, "time": "00:01:07.078000"}, {"place": -1, "splitDistance": 1125, "time": "00:01:14.569000"}, {"place": 10, "splitDistance": 1250, "time": "00:01:22.185000"}, {"place": -1, "splitDistance": 1375, "time": "00:01:29.665000"}, {"place": 10, "splitDistance": 1500, "time": "00:01:37.333000"}, {"place": -1, "splitDistance": 1625, "time": "00:01:45.031000"}, {"place": 12, "splitDistance": 1750, "time": "00:01:52.927000"}, {"place": -1, "splitDistance": 1875, "time": "00:02:00.631000"}, {"place": 13, "splitDistance": 2000, "time": "00:02:08.379000"}, {"place": -1, "splitDistance": 2125, "time": "00:02:16.067000"}, {"place": 12, "splitDistance": 2250, "time": "00:02:23.860000"}, {"place": -1, "splitDistance": 2375, "time": "00:02:31.486000"}, {"place": 12, "splitDistance": 2500, "time": "00:02:39.271000"}, {"place": -1, "splitDistance": 2625, "time": "00:02:47.038000"}, {"place": 13, "splitDistance": 2750, "time": "00:02:54.946000"}, {"place": -1, "splitDistance": 2875, "time": "00:03:02.580000"}, {"place": 12, "splitDistance": 3000, "time": "00:03:10.312000"}, {"place": -1, "splitDistance": 3125, "time": "00:03:17.886000"}, {"place": 11, "splitDistance": 3250, "time": "00:03:25.460000"}, {"place": -1, "splitDistance": 3375, "time": "00:03:33.160000"}, {"place": 12, "splitDistance": 3500, "time": "00:03:40.690000"}, {"place": -1, "splitDistance": 3625, "time": "00:03:48.414000"}, {"place": 11, "splitDistance": 3750, "time": "00:03:56.156000"}, {"place": -1, "splitDistance": 3875, "time": "00:04:03.606000"}, {"place": 11, "splitDistance": 4000, "time": "00:04:11.089000"}], "Team": "Switzerland"}, {"Country": "GER ", "Laps": [{"place": -1, "splitDistance": 125, "time": "00:00:13.372000"}, {"place": 10, "splitDistance": 250, "time": "00:00:21.413000"}, {"place": -1, "splitDistance": 375, "time": "00:00:28.847000"}, {"place": 8, "splitDistance": 500, "time": "00:00:36.305000"}, {"place": -1, "splitDistance": 625, "time": "00:00:43.778000"}, {"place": 8, "splitDistance": 750, "time": "00:00:51.346000"}, {"place": -1, "splitDistance": 875, "time": "00:00:58.708000"}, {"place": 8, "splitDistance": 1000, "time": "00:01:06.183000"}, {"place": -1, "splitDistance": 1125, "time": "00:01:13.723000"}, {"place": 8, "splitDistance": 1250, "time": "00:01:21.189000"}, {"place": -1, "splitDistance": 1375, "time": "00:01:28.829000"}, {"place": 7, "splitDistance": 1500, "time": "00:01:36.479000"}, {"place": -1, "splitDistance": 1625, "time": "00:01:44.234000"}, {"place": 8, "splitDistance": 1750, "time": "00:01:51.723000"}, {"place": -1, "splitDistance": 1875, "time": "00:01:59.293000"}, {"place": 8, "splitDistance": 2000, "time": "00:02:06.730000"}, {"place": -1, "splitDistance": 2125, "time": "00:02:14.266000"}, {"place": 8, "splitDistance": 2250, "time": "00:02:21.764000"}, {"place": -1, "splitDistance": 2375, "time": "00:02:29.223000"}, {"place": 6, "splitDistance": 2500, "time": "00:02:36.802000"}, {"place": -1, "splitDistance": 2625, "time": "00:02:44.511000"}, {"place": 7, "splitDistance": 2750, "time": "00:02:52.124000"}, {"place": -1, "splitDistance": 2875, "time": "00:02:59.846000"}, {"place": 7, "splitDistance": 3000, "time": "00:03:07.441000"}, {"place": -1, "splitDistance": 3125, "time": "00:03:15.154000"}, {"place": 7, "splitDistance": 3250, "time": "00:03:22.779000"}, {"place": -1, "splitDistance": 3375, "time": "00:03:30.318000"}, {"place": 6, "splitDistance": 3500, "time": "00:03:38.020000"}, {"place": -1, "splitDistance": 3625, "time": "00:03:45.725000"}, {"place": 7, "splitDistance": 3750, "time": "00:03:53.657000"}, {"place": -1, "splitDistance": 3875, "time": "00:04:01.564000"}, {"place": 7, "splitDistance": 4000, "time": "00:04:09.512000"}], "Team": "Germany"}, {"Country": "BEL ", "Laps": [{"place": -1, "splitDistance": 125, "time": "00:00:13.808000"}, {"place": 13, "splitDistance": 250, "time": "00:00:21.696000"}, {"place": -1, "splitDistance": 375, "time": "00:00:29.251000"}, {"place": 12, "splitDistance": 500, "time": "00:00:36.741000"}, {"place": -1, "splitDistance": 625, "time": "00:00:44.417000"}, {"place": 12, "splitDistance": 750, "time": "00:00:52.054000"}, {"place": -1, "splitDistance": 875, "time": "00:00:59.787000"}, {"place": 12, "splitDistance": 1000, "time": "00:01:07.167000"}, {"place": -1, "splitDistance": 1125, "time": "00:01:14.672000"}, {"place": 12, "splitDistance": 1250, "time": "00:01:22.354000"}, {"place": -1, "splitDistance": 1375, "time": "00:01:29.925000"}, {"place": 13, "splitDistance": 1500, "time": "00:01:37.659000"}, {"place": -1, "splitDistance": 1625, "time": "00:01:45.404000"}, {"place": 13, "splitDistance": 1750, "time": "00:01:53.336000"}, {"place": -1, "splitDistance": 1875, "time": "00:02:00.846000"}, {"place": 12, "splitDistance": 2000, "time": "00:02:08.276000"}, {"place": -1, "splitDistance": 2125, "time": "00:02:15.837000"}, {"place": 10, "splitDistance": 2250, "time": "00:02:23.243000"}, {"place": -1, "splitDistance": 2375, "time": "00:02:30.738000"}, {"place": 10, "splitDistance": 2500, "time": "00:02:38.134000"}, {"place": -1, "splitDistance": 2625, "time": "00:02:45.519000"}, {"place": 8, "splitDistance": 2750, "time": "00:02:52.996000"}, {"place": -1, "splitDistance": 2875, "time": "00:03:00.738000"}, {"place": 8, "splitDistance": 3000, "time": "00:03:08.511000"}, {"place": -1, "splitDistance": 3125, "time": "00:03:16.127000"}, {"place": 8, "splitDistance": 3250, "time": "00:03:23.987000"}, {"place": -1, "splitDistance": 3375, "time": "00:03:31.967000"}, {"place": 9, "splitDistance": 3500, "time": "00:03:39.737000"}, {"place": -1, "splitDistance": 3625, "time": "00:03:47.577000"}, {"place": 9, "splitDistance": 3750, "time": "00:03:55.357000"}, {"place": -1, "splitDistance": 3875, "time": "00:04:02.947000"}, {"place": 10, "splitDistance": 4000, "time": "00:04:10.642000"}], "Team": "Belgium"}, {"Country": "NED ", "Laps": [{"place": -1, "splitDistance": 125, "time": "00:00:13.042000"}, {"place": 3, "splitDistance": 250, "time": "00:00:20.892000"}, {"place": -1, "splitDistance": 375, "time": "00:00:28.498000"}, {"place": 6, "splitDistance": 500, "time": "00:00:36.008000"}, {"place": -1, "splitDistance": 625, "time": "00:00:43.589000"}, {"place": 6, "splitDistance": 750, "time": "00:00:51.048000"}, {"place": -1, "splitDistance": 875, "time": "00:00:58.586000"}, {"place": 7, "splitDistance": 1000, "time": "00:01:06.026000"}, {"place": -1, "splitDistance": 1125, "time": "00:01:13.584000"}, {"place": 7, "splitDistance": 1250, "time": "00:01:21.111000"}, {"place": -1, "splitDistance": 1375, "time": "00:01:28.821000"}, {"place": 8, "splitDistance": 1500, "time": "00:01:36.481000"}, {"place": -1, "splitDistance": 1625, "time": "00:01:44.225000"}, {"place": 9, "splitDistance": 1750, "time": "00:01:51.904000"}, {"place": -1, "splitDistance": 1875, "time": "00:01:59.708000"}, {"place": 9, "splitDistance": 2000, "time": "00:02:07.240000"}, {"place": -1, "splitDistance": 2125, "time": "00:02:14.904000"}, {"place": 9, "splitDistance": 2250, "time": "00:02:22.533000"}, {"place": -1, "splitDistance": 2375, "time": "00:02:30.272000"}, {"place": 9, "splitDistance": 2500, "time": "00:02:37.975000"}, {"place": -1, "splitDistance": 2625, "time": "00:02:45.763000"}, {"place": 10, "splitDistance": 2750, "time": "00:02:53.465000"}, {"place": -1, "splitDistance": 2875, "time": "00:03:01.089000"}, {"place": 10, "splitDistance": 3000, "time": "00:03:08.882000"}, {"place": -1, "splitDistance": 3125, "time": "00:03:16.428000"}, {"place": 10, "splitDistance": 3250, "time": "00:03:24.201000"}, {"place": -1, "splitDistance": 3375, "time": "00:03:31.820000"}, {"place": 8, "splitDistance": 3500, "time": "00:03:39.603000"}, {"place": -1, "splitDistance": 3625, "time": "00:03:47.124000"}, {"place": 8, "splitDistance": 3750, "time": "00:03:54.610000"}, {"place": -1, "splitDistance": 3875, "time": "00:04:02.076000"}, {"place": 8, "splitDistance": 4000, "time": "00:04:09.554000"}], "Team": "Netherlands"}, {"Country": "LOK ", "Laps": [{"place": -1, "splitDistance": 125, "time": "00:00:13.659000"}, {"place": 12, "splitDistance": 250, "time": "00:00:21.555000"}, {"place": -1, "splitDistance": 375, "time": "00:00:29.247000"}, {"place": 13, "splitDistance": 500, "time": "00:00:36.931000"}, {"place": -1, "splitDistance": 625, "time": "00:00:44.704000"}, {"place": 13, "splitDistance": 750, "time": "00:00:52.176000"}, {"place": -1, "splitDistance": 875, "time": "00:00:59.734000"}, {"place": 13, "splitDistance": 1000, "time": "00:01:07.230000"}, {"place": -1, "splitDistance": 1125, "time": "00:01:14.927000"}, {"place": 13, "splitDistance": 1250, "time": "00:01:22.439000"}, {"place": -1, "splitDistance": 1375, "time": "00:01:30.029000"}, {"place": 12, "splitDistance": 1500, "time": "00:01:37.642000"}, {"place": -1, "splitDistance": 1625, "time": "00:01:45.406000"}, {"place": 11, "splitDistance": 1750, "time": "00:01:52.902000"}, {"place": -1, "splitDistance": 1875, "time": "00:02:00.511000"}, {"place": 10, "splitDistance": 2000, "time": "00:02:08.116000"}, {"place": -1, "splitDistance": 2125, "time": "00:02:15.906000"}, {"place": 11, "splitDistance": 2250, "time": "00:02:23.506000"}, {"place": -1, "splitDistance": 2375, "time": "00:02:31.181000"}, {"place": 11, "splitDistance": 2500, "time": "00:02:38.980000"}, {"place": -1, "splitDistance": 2625, "time": "00:02:46.975000"}, {"place": 11, "splitDistance": 2750, "time": "00:02:54.651000"}, {"place": -1, "splitDistance": 2875, "time": "00:03:02.188000"}, {"place": 11, "splitDistance": 3000, "time": "00:03:09.934000"}, {"place": -1, "splitDistance": 3125, "time": "00:03:17.661000"}, {"place": 12, "splitDistance": 3250, "time": "00:03:25.604000"}, {"place": -1, "splitDistance": 3375, "time": "00:03:33.165000"}, {"place": 11, "splitDistance": 3500, "time": "00:03:40.598000"}, {"place": -1, "splitDistance": 3625, "time": "00:03:48.117000"}, {"place": 10, "splitDistance": 3750, "time": "00:03:55.528000"}, {"place": -1, "splitDistance": 3875, "time": "00:04:03.024000"}, {"place": 9, "splitDistance": 4000, "time": "00:04:10.605000"}], "Team": "LOKOSPHINX"}, {"Country": "GBR ", "Laps": [{"place": -1, "splitDistance": 125, "time": "00:00:13.058000"}, {"place": 2, "splitDistance": 250, "time": "00:00:20.750000"}, {"place": -1, "splitDistance": 375, "time": "00:00:28.353000"}, {"place": 2, "splitDistance": 500, "time": "00:00:35.743000"}, {"place": -1, "splitDistance": 625, "time": "00:00:43.252000"}, {"place": 5, "splitDistance": 750, "time": "00:00:50.733000"}, {"place": -1, "splitDistance": 875, "time": "00:00:58.284000"}, {"place": 5, "splitDistance": 1000, "time": "00:01:05.635000"}, {"place": -1, "splitDistance": 1125, "time": "00:01:13.069000"}, {"place": 5, "splitDistance": 1250, "time": "00:01:20.577000"}, {"place": -1, "splitDistance": 1375, "time": "00:01:28.087000"}, {"place": 5, "splitDistance": 1500, "time": "00:01:35.777000"}, {"place": -1, "splitDistance": 1625, "time": "00:01:43.322000"}, {"place": 5, "splitDistance": 1750, "time": "00:01:50.954000"}, {"place": -1, "splitDistance": 1875, "time": "00:01:58.455000"}, {"place": 4, "splitDistance": 2000, "time": "00:02:06.017000"}, {"place": -1, "splitDistance": 2125, "time": "00:02:13.625000"}, {"place": 5, "splitDistance": 2250, "time": "00:02:21.347000"}, {"place": -1, "splitDistance": 2375, "time": "00:02:28.892000"}, {"place": 4, "splitDistance": 2500, "time": "00:02:36.407000"}, {"place": -1, "splitDistance": 2625, "time": "00:02:44.037000"}, {"place": 4, "splitDistance": 2750, "time": "00:02:51.592000"}, {"place": -1, "splitDistance": 2875, "time": "00:02:59.197000"}, {"place": 4, "splitDistance": 3000, "time": "00:03:06.891000"}, {"place": -1, "splitDistance": 3125, "time": "00:03:14.611000"}, {"place": 4, "splitDistance": 3250, "time": "00:03:22.202000"}, {"place": -1, "splitDistance": 3375, "time": "00:03:29.739000"}, {"place": 4, "splitDistance": 3500, "time": "00:03:37.365000"}, {"place": -1, "splitDistance": 3625, "time": "00:03:44.952000"}, {"place": 4, "splitDistance": 3750, "time": "00:03:52.753000"}, {"place": -1, "splitDistance": 3875, "time": "00:04:00.389000"}, {"place": 4, "splitDistance": 4000, "time": "00:04:08.176000"}], "Team": "Great Britain"}, {"Country": "RVL ", "Laps": [{"place": -1, "splitDistance": 125, "time": "00:00:13.498000"}, {"place": 7, "splitDistance": 250, "time": "00:00:21.283000"}, {"place": -1, "splitDistance": 375, "time": "00:00:28.689000"}, {"place": 4, "splitDistance": 500, "time": "00:00:35.790000"}, {"place": -1, "splitDistance": 625, "time": "00:00:42.819000"}, {"place": 2, "splitDistance": 750, "time": "00:00:49.969000"}, {"place": -1, "splitDistance": 875, "time": "00:00:57.006000"}, {"place": 1, "splitDistance": 1000, "time": "00:01:04.067000"}, {"place": -1, "splitDistance": 1125, "time": "00:01:11.299000"}, {"place": 1, "splitDistance": 1250, "time": "00:01:18.425000"}, {"place": -1, "splitDistance": 1375, "time": "00:01:25.581000"}, {"place": 1, "splitDistance": 1500, "time": "00:01:32.853000"}, {"place": -1, "splitDistance": 1625, "time": "00:01:40.013000"}, {"place": 1, "splitDistance": 1750, "time": "00:01:47.209000"}, {"place": -1, "splitDistance": 1875, "time": "00:01:54.545000"}, {"place": 1, "splitDistance": 2000, "time": "00:02:01.716000"}, {"place": -1, "splitDistance": 2125, "time": "00:02:08.884000"}, {"place": 1, "splitDistance": 2250, "time": "00:02:16.237000"}, {"place": -1, "splitDistance": 2375, "time": "00:02:23.480000"}, {"place": 1, "splitDistance": 2500, "time": "00:02:30.764000"}, {"place": -1, "splitDistance": 2625, "time": "00:02:38.212000"}, {"place": 1, "splitDistance": 2750, "time": "00:02:45.658000"}, {"place": -1, "splitDistance": 2875, "time": "00:02:53.109000"}, {"place": 1, "splitDistance": 3000, "time": "00:03:00.783000"}, {"place": -1, "splitDistance": 3125, "time": "00:03:08.204000"}, {"place": 1, "splitDistance": 3250, "time": "00:03:15.665000"}, {"place": -1, "splitDistance": 3375, "time": "00:03:23.232000"}, {"place": 1, "splitDistance": 3500, "time": "00:03:30.635000"}, {"place": -1, "splitDistance": 3625, "time": "00:03:38.021000"}, {"place": 1, "splitDistance": 3750, "time": "00:03:45.610000"}, {"place": -1, "splitDistance": 3875, "time": "00:03:52.939000"}, {"place": 1, "splitDistance": 4000, "time": "00:04:00.488000"}], "Team": "RUSVELO"}, {"Country": "NZL ", "Laps": [{"place": -1, "splitDistance": 125, "time": "00:00:13.005000"}, {"place": 1, "splitDistance": 250, "time": "00:00:20.561000"}, {"place": -1, "splitDistance": 375, "time": "00:00:27.830000"}, {"place": 1, "splitDistance": 500, "time": "00:00:35.045000"}, {"place": -1, "splitDistance": 625, "time": "00:00:42.450000"}, {"place": 1, "splitDistance": 750, "time": "00:00:49.732000"}, {"place": -1, "splitDistance": 875, "time": "00:00:57.104000"}, {"place": 2, "splitDistance": 1000, "time": "00:01:04.418000"}, {"place": -1, "splitDistance": 1125, "time": "00:01:11.848000"}, {"place": 2, "splitDistance": 1250, "time": "00:01:19.193000"}, {"place": -1, "splitDistance": 1375, "time": "00:01:26.658000"}, {"place": 2, "splitDistance": 1500, "time": "00:01:34.092000"}, {"place": -1, "splitDistance": 1625, "time": "00:01:41.653000"}, {"place": 2, "splitDistance": 1750, "time": "00:01:49.060000"}, {"place": -1, "splitDistance": 1875, "time": "00:01:56.388000"}, {"place": 2, "splitDistance": 2000, "time": "00:02:03.833000"}, {"place": -1, "splitDistance": 2125, "time": "00:02:11.208000"}, {"place": 2, "splitDistance": 2250, "time": "00:02:18.579000"}, {"place": -1, "splitDistance": 2375, "time": "00:02:25.935000"}, {"place": 2, "splitDistance": 2500, "time": "00:02:33.506000"}, {"place": -1, "splitDistance": 2625, "time": "00:02:41.080000"}, {"place": 2, "splitDistance": 2750, "time": "00:02:48.858000"}, {"place": -1, "splitDistance": 2875, "time": "00:02:56.376000"}, {"place": 3, "splitDistance": 3000, "time": "00:03:03.964000"}, {"place": -1, "splitDistance": 3125, "time": "00:03:11.345000"}, {"place": 3, "splitDistance": 3250, "time": "00:03:18.738000"}, {"place": -1, "splitDistance": 3375, "time": "00:03:26.318000"}, {"place": 3, "splitDistance": 3500, "time": "00:03:33.862000"}, {"place": -1, "splitDistance": 3625, "time": "00:03:41.592000"}, {"place": 3, "splitDistance": 3750, "time": "00:03:49.243000"}, {"place": -1, "splitDistance": 3875, "time": "00:03:56.735000"}, {"place": 3, "splitDistance": 4000, "time": "00:04:04.247000"}], "Team": "New Zealand"}, {"Country": "AUS ", "Laps": [{"place": -1, "splitDistance": 125, "time": "00:00:13.376000"}, {"place": 5, "splitDistance": 250, "time": "00:00:21.208000"}, {"place": -1, "splitDistance": 375, "time": "00:00:28.674000"}, {"place": 5, "splitDistance": 500, "time": "00:00:35.894000"}, {"place": -1, "splitDistance": 625, "time": "00:00:43.172000"}, {"place": 3, "splitDistance": 750, "time": "00:00:50.378000"}, {"place": -1, "splitDistance": 875, "time": "00:00:57.697000"}, {"place": 3, "splitDistance": 1000, "time": "00:01:04.976000"}, {"place": -1, "splitDistance": 1125, "time": "00:01:12.465000"}, {"place": 3, "splitDistance": 1250, "time": "00:01:19.847000"}, {"place": -1, "splitDistance": 1375, "time": "00:01:27.346000"}, {"place": 3, "splitDistance": 1500, "time": "00:01:34.768000"}, {"place": -1, "splitDistance": 1625, "time": "00:01:42.242000"}, {"place": 3, "splitDistance": 1750, "time": "00:01:49.611000"}, {"place": -1, "splitDistance": 1875, "time": "00:01:57.061000"}, {"place": 3, "splitDistance": 2000, "time": "00:02:04.367000"}, {"place": -1, "splitDistance": 2125, "time": "00:02:11.827000"}, {"place": 3, "splitDistance": 2250, "time": "00:02:19.227000"}, {"place": -1, "splitDistance": 2375, "time": "00:02:26.781000"}, {"place": 3, "splitDistance": 2500, "time": "00:02:34.225000"}, {"place": -1, "splitDistance": 2625, "time": "00:02:41.660000"}, {"place": 3, "splitDistance": 2750, "time": "00:02:48.953000"}, {"place": -1, "splitDistance": 2875, "time": "00:02:56.304000"}, {"place": 2, "splitDistance": 3000, "time": "00:03:03.499000"}, {"place": -1, "splitDistance": 3125, "time": "00:03:10.826000"}, {"place": 2, "splitDistance": 3250, "time": "00:03:18.274000"}, {"place": -1, "splitDistance": 3375, "time": "00:03:25.639000"}, {"place": 2, "splitDistance": 3500, "time": "00:03:33.193000"}, {"place": -1, "splitDistance": 3625, "time": "00:03:40.534000"}, {"place": 2, "splitDistance": 3750, "time": "00:03:47.883000"}, {"place": -1, "splitDistance": 3875, "time": "00:03:55.349000"}, {"place": 2, "splitDistance": 4000, "time": "00:04:02.585000"}], "Team": "Australia"}]